__init__.py
example.py
rapidocr_onnxruntime_huawei/__init__.py
rapidocr_onnxruntime_huawei/main.py
rapidocr_onnxruntime_huawei/cal_rec_boxes/__init__.py
rapidocr_onnxruntime_huawei/cal_rec_boxes/main.py
rapidocr_onnxruntime_huawei/ch_ppocr_cls/__init__.py
rapidocr_onnxruntime_huawei/ch_ppocr_cls/text_cls.py
rapidocr_onnxruntime_huawei/ch_ppocr_cls/utils.py
rapidocr_onnxruntime_huawei/ch_ppocr_det/__init__.py
rapidocr_onnxruntime_huawei/ch_ppocr_det/text_detect.py
rapidocr_onnxruntime_huawei/ch_ppocr_det/utils.py
rapidocr_onnxruntime_huawei/ch_ppocr_rec/__init__.py
rapidocr_onnxruntime_huawei/ch_ppocr_rec/text_recognize.py
rapidocr_onnxruntime_huawei/ch_ppocr_rec/utils.py
rapidocr_onnxruntime_huawei/utils/__init__.py
rapidocr_onnxruntime_huawei/utils/infer_engine.py
rapidocr_onnxruntime_huawei/utils/load_image.py
rapidocr_onnxruntime_huawei/utils/logger.py
rapidocr_onnxruntime_huawei/utils/parse_parameters.py
rapidocr_onnxruntime_huawei/utils/process_img.py
rapidocr_onnxruntime_huawei/utils/vis_res.py
rapidocr_onnxruntime_huawei-1.4.1.dist-info/licenses/LICENSE
rapidocr_onnxruntime_huawei-1.4.1.dist-info/METADATA
rapidocr_onnxruntime_huawei-1.4.1.dist-info/WHEEL
rapidocr_onnxruntime_huawei-1.4.1.dist-info/top_level.txt
rapidocr_onnxruntime_huawei-1.4.1.dist-info/RECORD
