Metadata-Version: 2.4
Name: rapidocr_onnxruntime_huawei
Version: 1.4.1
Summary: This is a RapidOcr adapter for the onnxruntime inference model on huawei environment
Author-email: levsion <levsion@163.com>
License-Expression: MIT
Project-URL: Homepage, https://github.com/xxx_your_account/mlpredictor
Requires-Python: <=3.13,>=3.9
License-File: LICENSE
Requires-Dist: pyclipper>=1.2.1
Requires-Dist: opencv_python>=4.5.1.48
Requires-Dist: six>=1.15.0
Requires-Dist: Shapely>=1.7.1
Requires-Dist: numpy>=1.19.0
Requires-Dist: onnxruntime-cann>=1.18.0
Requires-Dist: PyYAML
Requires-Dist: Pillow
Dynamic: license-file
